stap/__about__.py
stap/__init__.py
stap-0.0.1a0.dist-info/METADATA
stap-0.0.1a0.dist-info/WHEEL
stap-0.0.1a0.dist-info/licenses/LICENSE.txt
stap-0.0.1a0.dist-info/RECORD
