Metadata-Version: 2.1
Name: stap
Version: 0.0.1a0
Summary: Python tools for STAP
Project-URL: Documentation, https://github.com/bact/stap#readme
Project-URL: Issues, https://github.com/bact/stap/issues
Project-URL: Source, https://github.com/bact/stap
Author-email: Arthit Suriyawongkul <suriyawa@tcd.ie>
License-Expression: MIT
License-File: LICENSE.txt
Classifier: Development Status :: 4 - Beta
Classifier: Programming Language :: Python
Classifier: Programming Language :: Python :: 3.8
Classifier: Programming Language :: Python :: 3.9
Classifier: Programming Language :: Python :: 3.10
Classifier: Programming Language :: Python :: 3.11
Classifier: Programming Language :: Python :: 3.12
Classifier: Programming Language :: Python :: Implementation :: CPython
Classifier: Programming Language :: Python :: Implementation :: PyPy
Requires-Python: >=3.8
